common_services/__init__.py
common_services/create_log_message.py
common_services-1.0.0.dist-info/LICENSE
common_services-1.0.0.dist-info/METADATA
common_services-1.0.0.dist-info/WHEEL
common_services-1.0.0.dist-info/top_level.txt
common_services-1.0.0.dist-info/RECORD
