Metadata-Version: 2.1
Name: common-services
Version: 1.0.0
Summary: common services for structured logging and other modules to interact with AWS resources
Home-page: https://github.com/vamsi245/py-common-services-lib
Author: Nike
License: UNKNOWN
Platform: UNKNOWN
